periodical.py
setup.py
periodical.egg-info/PKG-INFO
periodical.egg-info/SOURCES.txt
periodical.egg-info/dependency_links.txt
periodical.egg-info/top_level.txt